{
  "posts": [
    {
      "id": 1,
      "title": "json-server",
      "author": "typicode"
    }
  ],
  "comments": [
    {
      "id": 1,
      "body": "some comment",
      "postId": 1
    }
  ],
  "profile": {
    "name": "typicode"
  },
  "products": [
    {
      "name": "pc Asus",
      "price": "15070",
      "img": "product1.webp",
      "like": 0,
      "quantity": "22",
      "description": "tuff",
      "id": 2
    },
    {
      "name": "llll",
      "price": "150000",
      "img": "product2.jpg",
      "like": 0,
      "quantity": "848",
      "description": "thn",
      "id": 3
    }
  ]
}